{
    "levels_alt": [
        {
            "n": 16,
            "start": { "h": 0, "s": 1, "v": 1 },
            "end": { "h": 0.33, "s": 1, "v": 1 }
        },
        {
            "n": 17,
            "end": { "h": 0.66, "s": 1, "v": 1 }
        },
        {
            "n": 17,
            "end": { "h": 1, "s": 1, "v": 1 }
        }
    ],

   "levels": [
        {
            "n": 8,
            "start": { "h": 0.66, "s": 1, "v": 0 },
            "end": { "h": 0.66, "s": 1, "v": 1 }
        },
        {
            "n": 21,
            "end": { "h": 0.33, "s": 1, "v": 1 }
        },
        {
            "n": 21,
            "end": { "h": 0, "s": 1, "v": 1 }
        }
    ],

    "spectrum": [
        {
            "n": 16,
            "start": { "h": 0, "s": 1, "v": 1 },
            "end": { "h": 0.33, "s": 1, "v": 1 }
        },
        {
            "n": 17,
            "end": { "h": 0.66, "s": 1, "v": 1 }
        },
        {
            "n": 17,
            "end": { "h": 1, "s": 1, "v": 1 }
        }
    ]
}

